CHANGES.txt
LICENSE.txt
MANIFEST.in
README.txt
setup.py
django_excel_templates/Deco.py
django_excel_templates/ExcelReports.py
django_excel_templates/__init__.py
django_excel_templates/color_converter.py
django_excel_templates/helpers.py
django_excel_templates/style_templates.py
django_excel_templates.egg-info/PKG-INFO
django_excel_templates.egg-info/SOURCES.txt
django_excel_templates.egg-info/dependency_links.txt
django_excel_templates.egg-info/requires.txt
django_excel_templates.egg-info/top_level.txt
django_excel_templates.egg-info/zip-safe