Metadata-Version: 1.0
Name: django-excel-templates
Version: 0.1
Summary: Generate Excel Tables from Django
Home-page: http://code.google.com/p/django-excel-templates/
Author: bray, dean.sellis, tkemenczy, chalkdust1011, et al
Author-email: bray@sent.com
License: UNKNOWN
Platform: UNKNOWN
Classifier: Development Status :: 2 - Pre-Alpha
Classifier: Environment :: Web Environment
Classifier: Intended Audience :: Developers
Classifier: License :: OSI Approved :: MIT License
Classifier: Operating System :: OS Independent
Classifier: Programming Language :: Python
Classifier: Framework :: Django
